{
    "userId": 441581358,
    "authorName": "franoisboutry",
    "from": "&quot;franoisboutry&quot; &lt;franoisboutry@...&gt;",
    "profile": "franoisboutry",
    "replyTo": "LIST",
    "senderId": "WMfVubz8b7KWjh0ZYLttlivHseJOcnvH6m_muo-M6wMnHRZEqq6BtjGkB1aFQl1YZd0jLQwkqXGilYS-8FeN-TxlbBQ9-AJJrHGJZzG-oec",
    "spamInfo": {
        "isSpam": false,
        "reason": "0"
    },
    "subject": "Sugi clan",
    "postDate": "1270823407",
    "msgId": 10151,
    "canDelete": false,
    "contentTrasformed": false,
    "systemMessage": false,
    "headers": {
        "messageIdInHeader": "PGhwbmRsZisyMWhuQGVHcm91cHMuY29tPg=="
    },
    "prevInTopic": 0,
    "nextInTopic": 0,
    "prevInTime": 10150,
    "nextInTime": 10152,
    "topicId": 10151,
    "numMessagesInTopic": 1,
    "msgSnippet": "Who is able to supply info on the Sugi family ? They were major vassal of the Ôuchi and had more than one branch. I find in my files Sugi Shigeaki in 1399,",
    "rawEmail": "Return-Path: &lt;franoisboutry@...&gt;\r\nReceived: (qmail 28386 invoked by uid 7800); 10 Apr 2010 03:06:19 -0000\r\nX-Sender: franoisboutry@...\r\nX-Apparently-To: samuraihistory@yahoogroups.com\r\nX-Received: (qmail 34180 invoked from network); 9 Apr 2010 14:32:50 -0000\r\nX-Received: from unknown (98.137.34.45)\n  by m3.grp.sp2.yahoo.com with QMQP; 9 Apr 2010 14:32:50 -0000\r\nX-Received: from unknown (HELO n44d.bullet.mail.sp1.yahoo.com) (66.163.169.158)\n  by mta2.grp.sp2.yahoo.com with SMTP; 9 Apr 2010 14:32:50 -0000\r\nX-Received: from [69.147.65.171] by n44.bullet.mail.sp1.yahoo.com with NNFMP; 09 Apr 2010 14:30:08 -0000\r\nX-Received: from [98.137.34.32] by t13.bullet.mail.sp1.yahoo.com with NNFMP; 09 Apr 2010 14:30:08 -0000\r\nDate: Fri, 09 Apr 2010 14:30:07 -0000\r\nTo: samuraihistory@yahoogroups.com\r\nMessage-ID: &lt;hpndlf+21hn@...&gt;\r\nUser-Agent: eGroups-EW/0.82\r\nMIME-Version: 1.0\r\nContent-Type: text/plain; charset=&quot;ISO-8859-1&quot;\r\nContent-Transfer-Encoding: quoted-printable\r\nX-Mailer: Yahoo Groups Message Poster\r\nX-Yahoo-Newman-Property: groups-compose\r\nFrom: &quot;franoisboutry&quot; &lt;franoisboutry@...&gt;\r\nSubject: Sugi clan\r\nX-Yahoo-Group-Post: member; u=441581358; y=10o0vk7vlaV7Mm5am3MsaXZF4C1e7YtSRdLDZzPZ_cXFktNh5QTnow\r\nX-Yahoo-Profile: franoisboutry\r\nX-eGroups-Approved-By: kitsuno &lt;samurai-listowner@...&gt; via email; 10 Apr 2010 03:06:19 -0000\r\n\r\nWho is able to supply info on the Sugi family ? They were major vassal of t=\r\nhe =D4uchi and had more than one branch. I find in my files Sugi Shigeaki i=\r\nn 1399, his grandson Yoriaki in 1413. Later, around 1480/90, Sugi Shigetaka=\r\n, Shigechika and Takemichi were high officials of the =D4uchi. At the begin=\r\nning of the XVIe century, some were among counsellors of the =D4uchi&#39;s head=\r\n (Shigenori, Okinaga) while others served as shugodai of Buzen and Chikuzen=\r\n. In 1528, for instance, Okitsura, son of Okifusa, was shugodai of Chikuzen=\r\n but two years later, the shugodai of that province seems to have been Okik=\r\nazu. At the time of the fall of the =D4uchi, the counsellor Sugi Shigemasa =\r\nrevolted and joined Sue while Sugi Okitsura choose to die like his master =\r\n=D4uchi Yoshitaka in 1551. In 1554, a Sugi Takayasu was killed in Chikugo, =\r\nfighting against M=F4ri Motonari. All this is a bit confusing and I would b=\r\ne glad to understand the relationship between those various members of the =\r\nSugi clan as well as their history. Thank you\n\n\n"
}