{
    "userId": 2988921,
    "authorName": "James Eckman",
    "from": "James Eckman &lt;FUGU@...&gt;",
    "profile": "lost90804",
    "replyTo": "LIST",
    "senderId": "0h9fTQd5OUJIOkECq0qid1DFVwcCxHhqH7XeI2rkqbyI5c4ZUrJrKe3IIvLaZ54YEdt1oACvcdEmEmPU-U1E536bVaPCHw",
    "spamInfo": {
        "isSpam": false,
        "reason": "0"
    },
    "subject": "Re: Yagyuu Juubei",
    "postDate": "1041901936",
    "msgId": 1350,
    "canDelete": false,
    "contentTrasformed": false,
    "systemMessage": false,
    "headers": {
        "messageIdInHeader": "PDNFMUEyOTcwLjMwNjAzMDBAcHJvZGlneS5uZXQ+",
        "referencesHeader": "PDEwNDE4NzA5MTguNjM3LjkwNjI3Lm0xMkB5YWhvb2dyb3Vwcy5jb20+"
    },
    "prevInTopic": 0,
    "nextInTopic": 0,
    "prevInTime": 1349,
    "nextInTime": 1351,
    "topicId": 1350,
    "numMessagesInTopic": 1,
    "msgSnippet": "He existed apparently, Sonny Chiba did a great TV series about him called the Yagyuu Conspiracy in English. I ve seen him referenced  in books. Sorry I can t",
    "rawEmail": "Return-Path: &lt;fugu@...&gt;\r\nReceived: (qmail 82659 invoked by uid 7800); 7 Jan 2003 02:49:45 -0000\r\nX-Sender: fugu@...\r\nX-Apparently-To: samuraihistory@yahoogroups.com\r\nReceived: (EGP: mail-8_2_3_0); 7 Jan 2003 01:16:45 -0000\r\nReceived: (qmail 52942 invoked from network); 7 Jan 2003 01:16:44 -0000\r\nReceived: from unknown (66.218.66.217)\n  by m5.grp.scd.yahoo.com with QMQP; 7 Jan 2003 01:16:44 -0000\r\nReceived: from unknown (HELO smtp802.mail.sc5.yahoo.com) (66.163.168.181)\n  by mta2.grp.scd.yahoo.com with SMTP; 7 Jan 2003 01:16:44 -0000\r\nReceived: from dialup-63.208.135.105.dial1.sanfrancisco1.level3.net (HELO prodigy.net) (fugu@...@63.208.135.105 with plain)\n  by smtp-sbc-v1.mail.vip.sc5.yahoo.com with SMTP; 7 Jan 2003 01:16:44 -0000\r\nMessage-ID: &lt;3E1A2970.3060300@...&gt;\r\nDate: Mon, 06 Jan 2003 17:12:16 -0800\r\nUser-Agent: Mozilla/5.0 (Windows; U; Win 9x 4.90; en-US; rv:1.0.2) Gecko/20021120 Netscape/7.01\r\nX-Accept-Language: en,ja,zh\r\nMIME-Version: 1.0\r\nTo: samuraihistory@yahoogroups.com\r\nSubject: Re: Yagyuu Juubei\r\nReferences: &lt;1041870918.637.90627.m12@yahoogroups.com&gt;\r\nContent-Type: text/plain; charset=us-ascii; format=flowed\r\nContent-Transfer-Encoding: 7bit\r\nFrom: James Eckman &lt;FUGU@...&gt;\r\nX-Yahoo-Group-Post: member; u=2988921\r\nX-Yahoo-Profile: lost90804\r\nX-eGroups-Approved-By: kitsuno &lt;cewest@...&gt; via email; 7 Jan 2003 02:49:45 -0000\r\n\r\nHe existed apparently, Sonny Chiba did a great TV series about him \ncalled the Yagyuu Conspiracy in English. I&#39;ve seen him referenced  in \nbooks. Sorry I can&#39;t help more.\n\nJim Eckman\n\n\n"
}