{
    "userId": 83369860,
    "authorName": "Edwin Angulo",
    "from": "Edwin Angulo &lt;mayalan@...&gt;",
    "profile": "mayalan",
    "replyTo": "LIST",
    "senderId": "uinK4AVmLemIzgxNXNfWISUUueAecOCWp8X8KOP2l026e6OfL77ljLTqrp-YUDAdy6dHCU2mdzTaV8LP3Mek7gihwu1K3oo",
    "spamInfo": {
        "isSpam": false,
        "reason": "0"
    },
    "subject": "Re: [samuraihistory] Got a question...",
    "postDate": "1055824138",
    "msgId": 1894,
    "canDelete": false,
    "contentTrasformed": false,
    "systemMessage": false,
    "headers": {
        "messageIdInHeader": "PDIwMDMwNjE3MDQyODU4LjIzMDA4LnFtYWlsQHdlYjEzMTE1Lm1haWwueWFob28uY29tPg==",
        "inReplyToHeader": "PDAwMDcwMWMzMzQxYyQ1ZDE0ODNhMCQzMDdhZmVhOUBIUHBhdmlsaW9aRTUxODU+"
    },
    "prevInTopic": 1892,
    "nextInTopic": 0,
    "prevInTime": 1893,
    "nextInTime": 1895,
    "topicId": 1879,
    "numMessagesInTopic": 12,
    "msgSnippet": "Well, this is very useful. Thank you all ! Edwin Angulo. ... Do you Yahoo!? SBC Yahoo! DSL - Now only $29.95 per month! [Non-text portions of this message have",
    "rawEmail": "Return-Path: &lt;mayalan@...&gt;\r\nReceived: (qmail 16981 invoked by uid 7800); 17 Jun 2003 04:34:49 -0000\r\nX-Sender: mayalan@...\r\nX-Apparently-To: samuraihistory@yahoogroups.com\r\nReceived: (qmail 4241 invoked from network); 17 Jun 2003 04:28:59 -0000\r\nReceived: from unknown (66.218.66.218)\n  by m13.grp.scd.yahoo.com with QMQP; 17 Jun 2003 04:28:58 -0000\r\nReceived: from unknown (HELO web13115.mail.yahoo.com) (216.136.174.183)\n  by mta3.grp.scd.yahoo.com with SMTP; 17 Jun 2003 04:28:58 -0000\r\nMessage-ID: &lt;20030617042858.23008.qmail@...&gt;\r\nReceived: from [148.221.192.121] by web13115.mail.yahoo.com via HTTP; Mon, 16 Jun 2003 21:28:58 PDT\r\nDate: Mon, 16 Jun 2003 21:28:58 -0700 (PDT)\r\nSubject: Re: [samuraihistory] Got a question...\r\nTo: samuraihistory@yahoogroups.com\r\nIn-Reply-To: &lt;000701c3341c$5d1483a0$307afea9@HPpavilioZE5185&gt;\r\nMIME-Version: 1.0\r\nFrom: Edwin Angulo &lt;mayalan@...&gt;\r\nX-Yahoo-Group-Post: member; u=83369860\r\nX-Yahoo-Profile: mayalan\r\nContent-Type: text/plain; charset=US-ASCII\r\nContent-Transfer-Encoding: 7bit\r\nX-eGroups-Approved-By: kitsuno &lt;samurai-listowner@...&gt; via email; 17 Jun 2003 04:34:49 -0000\r\n\r\n\nWell, this is very useful.\n\nThank you all !\n\nEdwin Angulo.\n\n\n\n---------------------------------\nDo you Yahoo!?\nSBC Yahoo! DSL - Now only $29.95 per month!\n\n[Non-text portions of this message have been removed]\n\n\n"
}