{
    "userId": 0,
    "authorName": "Christopher West",
    "from": "&quot;Christopher West&quot; &lt;kitsuno@...&gt;",
    "replyTo": "LIST",
    "senderId": "S2JH6JAm0mwzOVZZfL7BG5Lv_xwLyh2czCcpuFN8Tcqjj7MP458nkTFdoUETiGdfEibLGxlyKdWMr-on8jStGXf0mbqPIfkJNKerF6HMuQ",
    "spamInfo": {
        "isSpam": false,
        "reason": "0"
    },
    "subject": "Miyamoto Musashi website",
    "postDate": "999387533",
    "msgId": 308,
    "canDelete": false,
    "contentTrasformed": false,
    "systemMessage": false,
    "headers": {
        "messageIdInHeader": "PDltcnJpZCtxZGFuQGVHcm91cHMuY29tPg=="
    },
    "prevInTopic": 0,
    "nextInTopic": 309,
    "prevInTime": 307,
    "nextInTime": 309,
    "topicId": 308,
    "numMessagesInTopic": 2,
    "msgSnippet": "A while back someone emailed me a link to a good history page on Miyamoto Musashi, which I lost almost immediately after taking a look - anyone have any links",
    "rawEmail": "Return-Path: &lt;kitsuno@...&gt;\r\nX-Sender: kitsuno@...\r\nX-Apparently-To: samuraihistory@yahoogroups.com\r\nReceived: (EGP: mail-7_3_2); 1 Sep 2001 23:38:57 -0000\r\nReceived: (qmail 33601 invoked from network); 1 Sep 2001 23:38:57 -0000\r\nReceived: from unknown (10.1.10.26)\n  by l8.egroups.com with QMQP; 1 Sep 2001 23:38:57 -0000\r\nReceived: from unknown (HELO n10.groups.yahoo.com) (10.1.10.49)\n  by mta1 with SMTP; 1 Sep 2001 23:38:57 -0000\r\nX-eGroups-Return: kitsuno@...\r\nReceived: from [10.1.10.114] by ej.egroups.com with NNFMP; 01 Sep 2001 23:38:57 -0000\r\nDate: Sat, 01 Sep 2001 23:38:53 -0000\r\nTo: samuraihistory@yahoogroups.com\r\nSubject: Miyamoto Musashi website\r\nMessage-ID: &lt;9mrrid+qdan@...&gt;\r\nUser-Agent: eGroups-EW/0.82\r\nMIME-Version: 1.0\r\nContent-Type: text/plain; charset=ISO-8859-1\r\nContent-Length: 191\r\nX-Mailer: eGroups Message Poster\r\nFrom: &quot;Christopher West&quot; &lt;kitsuno@...&gt;\r\n\r\nA while back someone emailed me a link to a good history page on \nMiyamoto Musashi, which I lost almost immediately after taking a \nlook - anyone have any links to Musashi out there...?\n\n\nc.\n\n\n"
}