{
    "userId": 0,
    "authorName": "Garvey, Paul",
    "from": "&quot;Garvey, Paul&quot; &lt;paul.garvey@...&gt;",
    "replyTo": "LIST",
    "senderId": "5l26SorzfqBcXiRfy3idYptJmOXjMlkASBTCXQUaLIgt8_eI56OMAKXb-IINiNHLArIX61IyMRqoYUDho3NGHK_mIpIW_RtiVs-iX19m",
    "spamInfo": {
        "isSpam": false,
        "reason": "0"
    },
    "subject": "RE: [samuraihistory] In Memoriam",
    "postDate": "1000465818",
    "msgId": 328,
    "canDelete": false,
    "contentTrasformed": false,
    "systemMessage": false,
    "headers": {
        "messageIdInHeader": "PDE1M0E1MzA0RUQ5OEQ1MTFCOUY1MDA1MDhCQUREM0JFMDI1MTdCMzhAZXhjaGFuZ2UxLmRwcmNzc2IuZWR1Lm9uLmNhPg=="
    },
    "prevInTopic": 327,
    "nextInTopic": 329,
    "prevInTime": 327,
    "nextInTime": 329,
    "topicId": 326,
    "numMessagesInTopic": 6,
    "msgSnippet": "I am a high-school history teacher in Canada. Today (Friday) has been declared a national day of mourning in our nation, not only for the over 100 Canadian",
    "rawEmail": "Return-Path: &lt;Paul.Garvey@...&gt;\r\nReceived: (qmail 6701 invoked from network); 14 Sep 2001 16:49:31 -0000\r\nReceived: from unknown (10.1.10.26)\n  by m8.onelist.org with QMQP; 14 Sep 2001 16:49:31 -0000\r\nReceived: from unknown (HELO n5.groups.yahoo.com) (10.1.10.44)\n  by mta1 with SMTP; 14 Sep 2001 16:49:28 -0000\r\nX-eGroups-Return: Paul.Garvey@...\r\nReceived: from [10.1.2.109] by hl.egroups.com with NNFMP; 14 Sep 2001 16:49:26 -0000\r\nX-eGroups-Approved-By: kitsuno@... via web; 14 Sep 2001 16:49:22 -0000\r\nX-Sender: Paul.Garvey@...\r\nX-Apparently-To: samuraihistory@yahoogroups.com\r\nReceived: (EGP: mail-7_3_2_2); 14 Sep 2001 11:50:13 -0000\r\nReceived: (qmail 59440 invoked from network); 14 Sep 2001 11:11:22 -0000\r\nReceived: from unknown (10.1.10.142)\n  by l10.egroups.com with QMQP; 14 Sep 2001 11:11:22 -0000\r\nReceived: from unknown (HELO exchange1.dpcdsb.org) (199.43.172.254)\n  by mta3 with SMTP; 14 Sep 2001 11:11:18 -0000\r\nReceived: by exchange1.dprcssb.edu.on.ca with Internet Mail Service (5.5.2653.19)\n\tid &lt;S2V9GVMS&gt;; Fri, 14 Sep 2001 07:10:18 -0400\r\nMessage-ID: &lt;153A5304ED98D511B9F500508BADD3BE02517B38@...&gt;\r\nTo: &quot;&#39;samuraihistory@yahoogroups.com&#39;&quot; &lt;samuraihistory@yahoogroups.com&gt;\r\nSubject: RE: [samuraihistory] In Memoriam\r\nDate: Fri, 14 Sep 2001 07:10:18 -0400\r\nMIME-Version: 1.0\r\nX-Mailer: Internet Mail Service (5.5.2653.19)\r\nContent-Type: text/plain\r\nFrom: &quot;Garvey, Paul&quot; &lt;paul.garvey@...&gt;\r\n\r\nI am a high-school history teacher in Canada. Today (Friday) has been\ndeclared a national day of mourning in our nation, not only for the over 100\nCanadian victims, but all other people affected. At this time, we are all\ncitizens of the world.  \n\nPaul\n&gt; ----------\n&gt; From: \tNate Ledbetter[SMTP:ltdomer98@...]\n&gt; Reply To: \tsamuraihistory@yahoogroups.com\n&gt; Sent: \tThursday, September 13, 2001 12:55 PM\n&gt; To: \tsamuraihistory@yahoogroups.com\n&gt; Subject: \tRe: [samuraihistory] In Memoriam\n&gt; \n&gt; As a member of the U.S. Military, but most importantly\n&gt; as an American, Thank you. Thank you and your country\n&gt; very much. I think all of us here know someone who was\n&gt; close to or is affected by these tragic events. Thank\n&gt; you. Your thoughts are deeply, deeply appreciated.\n&gt; \n&gt; Nate\n&gt; \n&gt; \n&gt; --- kagemaru &lt;kagemaru@...&gt; wrote:\n&gt; &gt; Too all those who have or believe they have lost\n&gt; &gt; friends, family and loves,\n&gt; &gt; in these tragic events that the whole world no doubt\n&gt; &gt; knows of, here in\n&gt; &gt; Ireland the flags are at half-mast through Friday\n&gt; &gt; 14th Sept, and the whole\n&gt; &gt; country will be at a complete standstill in memoriam\n&gt; &gt; of those heroes who\n&gt; &gt; diverted the fourth flight, and those who were\n&gt; &gt; unfortunate enough to be on\n&gt; &gt; the others, and working or visiting the World Trade\n&gt; &gt; Centre, and serving in\n&gt; &gt; the Pentagon.\n&gt; &gt; \n&gt; &gt; We pray for their souls, whatever thier religious\n&gt; &gt; origin.\n&gt; &gt; \n&gt; &gt; Kagemaru.\n&gt; &gt; \n&gt; &gt; \n&gt; &gt; \n&gt; &gt; \n&gt; \n&gt; \n&gt; __________________________________________________\n&gt; Terrorist Attacks on U.S. - How can you help?\n&gt; Donate cash, emergency relief information\n&gt; http://dailynews.yahoo.com/fc/US/Emergency_Information/\n&gt; \n&gt; \n&gt; Samurai Archives: http://www.angelfire.com/realm/kitsuno01/index.html\n&gt; ---\n&gt; To unsubscribe from this group, send an email to:\n&gt; samuraihistory-unsubscribe@yahoogroups.com\n&gt; \n&gt;  \n&gt; \n&gt; Your use of Yahoo! Groups is subject to http://docs.yahoo.com/info/terms/ \n&gt; \n&gt; \n\n\n"
}