{
    "userId": 174420642,
    "authorName": "roland holland",
    "from": "roland holland &lt;onyxtsunami@...&gt;",
    "profile": "onyxtsunami",
    "replyTo": "LIST",
    "senderId": "DmWpDUQ9Ie-1uscNU22OtrxS9bgYrUyMOzho_rKUcV25iyEEoCEIAuTpdLDas1ofOzznpc4Ki7SfuuftR45mZr87x2F1kSD4nPZQuAc",
    "spamInfo": {
        "isSpam": false,
        "reason": "0"
    },
    "subject": "Re: [samuraihistory] hey there",
    "postDate": "1075573846",
    "msgId": 3465,
    "canDelete": false,
    "contentTrasformed": false,
    "systemMessage": false,
    "headers": {
        "messageIdInHeader": "PDIwMDQwMTMxMTgzMDQ2LjQxMzgxLnFtYWlsQHdlYjQxODAzLm1haWwueWFob28uY29tPg==",
        "inReplyToHeader": "PDY2MkREREU2LTUzREItMTFEOC04Q0ExLTAwMDM5Mzk2MkY5OEBkb25rZXlpc2xhbmQuY29tPg=="
    },
    "prevInTopic": 3460,
    "nextInTopic": 3466,
    "prevInTime": 3464,
    "nextInTime": 3466,
    "topicId": 3452,
    "numMessagesInTopic": 4,
    "msgSnippet": "i work alone with no lord but more as a samurai for hire.and some people have serious cases but fun for me. ... Onixtsunami Dono, Just out of curiosity: who is",
    "rawEmail": "Return-Path: &lt;onyxtsunami@...&gt;\r\nReceived: (qmail 50925 invoked by uid 7800); 31 Jan 2004 18:40:19 -0000\r\nX-Sender: onyxtsunami@...\r\nX-Apparently-To: samuraihistory@yahoogroups.com\r\nReceived: (qmail 29188 invoked from network); 31 Jan 2004 18:30:50 -0000\r\nReceived: from unknown (66.218.66.172)\n  by m3.grp.scd.yahoo.com with QMQP; 31 Jan 2004 18:30:50 -0000\r\nReceived: from unknown (HELO web41803.mail.yahoo.com) (66.218.93.137)\n  by mta4.grp.scd.yahoo.com with SMTP; 31 Jan 2004 18:30:50 -0000\r\nMessage-ID: &lt;20040131183046.41381.qmail@...&gt;\r\nReceived: from [68.45.209.205] by web41803.mail.yahoo.com via HTTP; Sat, 31 Jan 2004 10:30:46 PST\r\nDate: Sat, 31 Jan 2004 10:30:46 -0800 (PST)\r\nTo: samuraihistory@yahoogroups.com\r\nIn-Reply-To: &lt;662DDDE6-53DB-11D8-8CA1-000393962F98@...&gt;\r\nMIME-Version: 1.0\r\nX-eGroups-Remote-IP: 66.218.93.137\r\nFrom: roland holland &lt;onyxtsunami@...&gt;\r\nSubject: Re: [samuraihistory] hey there\r\nX-Yahoo-Group-Post: member; u=174420642\r\nX-Yahoo-Profile: onyxtsunami\r\nContent-Type: text/plain; charset=US-ASCII\r\nContent-Transfer-Encoding: 7bit\r\nX-eGroups-Approved-By: kitsuno &lt;samurai-listowner@...&gt; via email; 31 Jan 2004 18:40:19 -0000\r\n\r\ni work alone with no lord but more as a samurai for hire.and some people have serious cases but fun for me.\n\nCesare Polenghi &lt;cepo@...&gt; wrote:On Jan 30, 2004, at 4:37 PM, onyxtsunami wrote:\n\n&gt; i&#39;m not new to samurais but new to this.i&#39;m  actually becoming a\n&gt; swordsman and enjoy training with my sword.\n\nOnixtsunami Dono,\nJust out of curiosity: who is your lord?\nAnd in which domain are you and your army located?\n\nRegards from Cepo,\n\n\n[Non-text portions of this message have been removed]\n\n\n---\nSamurai Archives: http://www.samurai-archives.com\nSamurai Archives store: http://www.cafeshops.com/samuraiarchives\n--- \n\n\nYahoo! Groups Links\n\nTo visit your group on the web, go to:\nhttp://groups.yahoo.com/group/samuraihistory/\n\nTo unsubscribe from this group, send an email to:\nsamuraihistory-unsubscribe@yahoogroups.com\n\nYour use of Yahoo! Groups is subject to:\nhttp://docs.yahoo.com/info/terms/ \n\n\n\n\n---------------------------------\nDo you Yahoo!?\nYahoo! SiteBuilder - Free web site building tool. Try it!\n\n[Non-text portions of this message have been removed]\n\n\n"
}