{
    "userId": 113141654,
    "authorName": "Thomas Davidson",
    "from": "&quot;Thomas Davidson&quot; &lt;tom.davidson@...&gt;",
    "profile": "thomas5403",
    "replyTo": "LIST",
    "senderId": "wilk7l44niD_g6nl5_KLdlf2VuBX-tlVr6RpfW_rTAshLbWv_PYT_wkkWG8Z6MHnelkfRmz_SAyOc65MJnQyLhkwCie3XPmeVXLbFVV5iLP2I6Pu",
    "spamInfo": {
        "isSpam": false,
        "reason": "0"
    },
    "subject": "Re: RE: Seppuku vs. Hara-Kiri",
    "postDate": "1092230075",
    "msgId": 5150,
    "canDelete": false,
    "contentTrasformed": false,
    "systemMessage": true,
    "headers": {
        "messageIdInHeader": "PGNmZDYzcitmbG8yQGVHcm91cHMuY29tPg==",
        "inReplyToHeader": "PDRDREM0NDQyLUVCOTYtMTFEOC1CNzVGLTAwMEE5NURGQUFFMEB0b3J5dS1tb24uY29tPg=="
    },
    "prevInTopic": 5147,
    "nextInTopic": 0,
    "prevInTime": 5149,
    "nextInTime": 5151,
    "topicId": 4983,
    "numMessagesInTopic": 24,
    "msgSnippet": "Hi Tom - As per my earlier post, I agree with you about the Edo era origins of Jun-to (especially of the finesse of leaving a shred in place) as I too learnt",
    "rawEmail": "Return-Path: &lt;tom.davidson@...&gt;\r\nReceived: (qmail 64928 invoked from network); 11 Aug 2004 13:46:37 -0000\r\nReceived: from unknown (66.218.66.167)\n  by m11.grp.scd.yahoo.com with QMQP; 11 Aug 2004 13:46:37 -0000\r\nReceived: from unknown (HELO n40.grp.scd.yahoo.com) (66.218.66.108)\n  by mta6.grp.scd.yahoo.com with SMTP; 11 Aug 2004 13:46:37 -0000\r\nReceived: from [66.218.67.136] by n40.grp.scd.yahoo.com with NNFMP; 11 Aug 2004 13:45:57 -0000\r\nX-Sender: tom.davidson@...\r\nX-Apparently-To: samuraihistory@yahoogroups.com\r\nReceived: (qmail 991 invoked from network); 11 Aug 2004 13:14:39 -0000\r\nReceived: from unknown (66.218.66.166)\n  by m13.grp.scd.yahoo.com with QMQP; 11 Aug 2004 13:14:39 -0000\r\nReceived: from unknown (HELO n5.grp.scd.yahoo.com) (66.218.66.89)\n  by mta5.grp.scd.yahoo.com with SMTP; 11 Aug 2004 13:14:39 -0000\r\nReceived: from [66.218.66.124] by n5.grp.scd.yahoo.com with NNFMP; 11 Aug 2004 13:14:38 -0000\r\nDate: Wed, 11 Aug 2004 13:14:35 -0000\r\nTo: samuraihistory@yahoogroups.com\r\nMessage-ID: &lt;cfd63r+flo2@...&gt;\r\nIn-Reply-To: &lt;4CDC4442-EB96-11D8-B75F-000A95DFAAE0@...&gt;\r\nUser-Agent: eGroups-EW/0.82\r\nMIME-Version: 1.0\r\nContent-Type: text/plain; charset=ISO-8859-1\r\nContent-Length: 365\r\nX-Mailer: Yahoo Groups Message Poster\r\nX-Yahoo-Newman-Property: groups-system\r\nX-eGroups-Remote-IP: 66.218.66.89\r\nFrom: &quot;Thomas Davidson&quot; &lt;tom.davidson@...&gt;\r\nSubject: Re: RE: Seppuku vs. Hara-Kiri\r\nX-Yahoo-Group-Post: member; u=113141654\r\nX-Yahoo-Profile: thomas5403\r\nX-eGroups-Approved-By: kitsuno &lt;samurai-listowner@...&gt; via web; 11 Aug 2004 13:45:56 -0000\r\nX-eGroups-Remote-IP: 66.218.66.108\r\n\r\nHi Tom - \n\nAs per my earlier post, I agree with you about the Edo era origins \nof Jun-to (especially of the finesse of leaving a shred in place) as \nI too learnt this in my Muso Shinden Ryu training.\n\nThinking aloud, I have accounts of the Loyal 47 and the Sakai \nJiken by Mori Ogai - and I can&#39;t recall the mention of kaishaku - I&#39;ll \ncheck it out later.\n\nThomas\n\n\n\n\n"
}