{
    "userId": 225755910,
    "authorName": "ronin64@netti.fi",
    "from": "ronin64@...",
    "replyTo": "LIST",
    "senderId": "NDRGS-0vlhfJ03XZw-PbCb4a9y_dP6-gJKndaN-bwzjZ759V5CBQmZLesKtmHpQXOBBi89pjAw",
    "spamInfo": {
        "isSpam": false,
        "reason": "12"
    },
    "subject": "Re: [a quest for a book",
    "postDate": "1119518850",
    "msgId": 7251,
    "canDelete": false,
    "contentTrasformed": false,
    "systemMessage": true,
    "headers": {
        "messageIdInHeader": "PDI3NjA4NjY1LjExMTk1MTg4NTA0MjYuSmF2YU1haWwucm9uaW42NEBuZXR0aS5maT4="
    },
    "prevInTopic": 0,
    "nextInTopic": 0,
    "prevInTime": 7250,
    "nextInTime": 7252,
    "topicId": 7251,
    "numMessagesInTopic": 1,
    "msgSnippet": "hi!i´ve been trying to get my hands onthe book called NITEN-KI.no luck.can anyone help me out here?i need to read it(in english)(its a book about Shinmen",
    "rawEmail": "Return-Path: &lt;ronin64@...&gt;\r\nReceived: (qmail 75529 invoked from network); 23 Jun 2005 10:40:27 -0000\r\nReceived: from unknown (66.218.66.172)\n  by m27.grp.scd.yahoo.com with QMQP; 23 Jun 2005 10:40:27 -0000\r\nReceived: from unknown (HELO n9a.bulk.scd.yahoo.com) (66.94.237.43)\n  by mta4.grp.scd.yahoo.com with SMTP; 23 Jun 2005 10:40:27 -0000\r\nComment: DomainKeys? See http://antispam.yahoo.com/domainkeys\r\nReceived: from [66.218.69.4] by n9.bulk.scd.yahoo.com with NNFMP; 23 Jun 2005 10:39:17 -0000\r\nReceived: from [66.218.66.78] by mailer4.bulk.scd.yahoo.com with NNFMP; 23 Jun 2005 10:39:17 -0000\r\nX-Sender: ronin64@...\r\nX-Apparently-To: samuraihistory@yahoogroups.com\r\nReceived: (qmail 6714 invoked from network); 23 Jun 2005 09:27:32 -0000\r\nReceived: from unknown (66.218.66.172)\n  by m18.grp.scd.yahoo.com with QMQP; 23 Jun 2005 09:27:31 -0000\r\nReceived: from unknown (HELO gw01.mail.saunalahti.fi) (195.197.172.115)\n  by mta4.grp.scd.yahoo.com with SMTP; 23 Jun 2005 09:27:31 -0000\r\nReceived: from espresso.webmail.saunalahti.fi (espresso.webmail.saunalahti.fi [195.197.55.113])\n\tby gw01.mail.saunalahti.fi (Postfix) with ESMTP id 6D6F0E3F2B\n\tfor &lt;samuraihistory@yahoogroups.com&gt;; Thu, 23 Jun 2005 12:27:30 +0300 (EEST)\r\nMessage-ID: &lt;27608665.1119518850426.JavaMail.ronin64@...&gt;\r\nDate: Thu, 23 Jun 2005 12:27:30 +0300 (EEST)\r\nTo: samuraihistory@yahoogroups.com\r\nMime-Version: 1.0\r\nContent-Type: text/plain; Charset=iso-8859-1; Format=Flowed\r\nContent-Transfer-Encoding: quoted-printable\r\nX-Mailer: Saunalahti webmail - http://www.saunalahti.fi\r\nX-eGroups-Msg-Info: 1:12:0\r\nFrom: ronin64@...\r\nSubject: Re: [a quest for a book\r\nX-Yahoo-Group-Post: member; u=225755910\r\nX-Yahoo-Newman-Property: groups-system\r\nX-eGroups-Approved-By: ltdomer98 &lt;ltdomer98@...&gt; via web; 23 Jun 2005 10:39:14 -0000\r\n\r\nhi!i=B4ve been trying to get my hands onthe book called NITEN-KI.no \nluck.c=\r\nan anyone help me out here?i need to read it(in english)(its a \nbook about =\r\nShinmen Musashi ,written by his &quot;followers&quot;)ill be ever \ngratefull!!...rega=\r\nrds JORE,from Finland\n\n__\nSaunalahti Xtra - Uusi GSM-vuokrapuhelin ja edist=\r\nykselliset Xtra-palvelut k=E4ytt=F6=F6si alk. 4,95 e/kk! http://saunalahti.=\r\nfi/xtra/\n\n\n\n\n"
}