{
    "userId": 222108855,
    "authorName": "E. Martinez",
    "from": "&quot;E. Martinez&quot; &lt;Lutzberg@...&gt;",
    "profile": "princelutzberg",
    "replyTo": "LIST",
    "senderId": "FgRDNWi6GNUMEK8bAJdLP_jHEs7PXng3290UemttAm16hKxQ4n4pxbjIOO_bX7b6QCuFCnq5OWWsofGwqLQg1dnBWsdAaeHLQg",
    "spamInfo": {
        "isSpam": false,
        "reason": "12"
    },
    "subject": "Re: [samuraihistory] Ashigaru Officers?",
    "postDate": "1235106502",
    "msgId": 9856,
    "canDelete": false,
    "contentTrasformed": false,
    "systemMessage": false,
    "headers": {
        "messageIdInHeader": "PDcyYzYwNTM4MDkwMjE5MjEwOHQ2MTA0ZDJlYmcyZmY3MWZiY2UwYTVlZGYxQG1haWwuZ21haWwuY29tPg==",
        "inReplyToHeader": "PDgzNzU2My44NTk1LnFtQHdlYjQ2MTAyLm1haWwuc3AxLnlhaG9vLmNvbT4=",
        "referencesHeader": "PGduajNiZitzamI1QGVHcm91cHMuY29tPgkgPDgzNzU2My44NTk1LnFtQHdlYjQ2MTAyLm1haWwuc3AxLnlhaG9vLmNvbT4="
    },
    "prevInTopic": 9855,
    "nextInTopic": 0,
    "prevInTime": 9855,
    "nextInTime": 9857,
    "topicId": 9853,
    "numMessagesInTopic": 3,
    "msgSnippet": "Awesome, Takezo Thanks for the assistance.",
    "rawEmail": "Return-Path: &lt;lutzberg@...&gt;\r\nReceived: (qmail 71887 invoked by uid 7800); 20 Feb 2009 05:42:51 -0000\r\nX-Sender: lutzberg@...\r\nX-Apparently-To: samuraihistory@yahoogroups.com\r\nX-Received: (qmail 99535 invoked from network); 20 Feb 2009 05:08:23 -0000\r\nX-Received: from unknown (66.218.67.97)\n  by m1.grp.re1.yahoo.com with QMQP; 20 Feb 2009 05:08:23 -0000\r\nX-Received: from unknown (HELO wa-out-1112.google.com) (209.85.146.177)\n  by mta18.grp.scd.yahoo.com with SMTP; 20 Feb 2009 05:08:23 -0000\r\nX-Received: by wa-out-1112.google.com with SMTP id m38so423418waf.28\n        for &lt;samuraihistory@yahoogroups.com&gt;; Thu, 19 Feb 2009 21:08:22 -0800 (PST)\r\nMIME-Version: 1.0\r\nX-Received: by 10.114.24.5 with SMTP id 5mr189099wax.106.1235106502932; Thu, 19 \n\tFeb 2009 21:08:22 -0800 (PST)\r\nIn-Reply-To: &lt;837563.8595.qm@...&gt;\r\nReferences: &lt;gnj3bf+sjb5@...&gt;\n\t &lt;837563.8595.qm@...&gt;\r\nDate: Fri, 20 Feb 2009 16:08:22 +1100\r\nMessage-ID: &lt;72c605380902192108t6104d2ebg2ff71fbce0a5edf1@...&gt;\r\nTo: samuraihistory@yahoogroups.com\r\nContent-Type: text/plain; charset=ISO-8859-1\r\nContent-Transfer-Encoding: 7bit\r\nX-eGroups-Msg-Info: 1:12:0:0:0\r\nFrom: &quot;E. Martinez&quot; &lt;Lutzberg@...&gt;\r\nSubject: Re: [samuraihistory] Ashigaru Officers?\r\nX-Yahoo-Group-Post: member; u=222108855; y=-xhGeGMuovkDIvu3W6K3yMYV19ymUL45nsbOtEZXNJ6EXPDXKHcvXbk\r\nX-Yahoo-Profile: princelutzberg\r\nX-eGroups-Approved-By: kitsuno &lt;samurai-listowner@...&gt; via email; 20 Feb 2009 05:42:51 -0000\r\n\r\nAwesome, Takezo\n\nThanks for the assistance.\n\nOn Fri, Feb 20, 2009 at 2:56 PM, Takezo Getsu &lt;getsutakezo@...&gt; wrote:\n&gt; I would say both, but it really depended on the army.  There was often a\n&gt; thin line between high ranking ashigaru and very low ranking samurai, so\n&gt; either would suffice.  Usually, it would be a high ranking ashigaru (the\n&gt; equivalent of a sergeant or a lieutennant in the U.S. Army), who would then\n&gt; be under the command of either a kumigashira or a monogashira (division\n&gt; commander, one way or another).\n&gt;\n&gt; --- On Thu, 2/19/09, Philip Sorel &lt;Lutzberg@...&gt; wrote:\n&gt;\n&gt; From: Philip Sorel &lt;Lutzberg@...&gt;\n&gt; Subject: [samuraihistory] Ashigaru Officers?\n&gt; To: samuraihistory@yahoogroups.com\n&gt; Date: Thursday, February 19, 2009, 7:56 AM\n&gt;\n&gt; Hi Everyone\n&gt;\n&gt; Just wanted to know. Were the officers in Ashigaru units Samurai? or\n&gt; did they have their own Ashigaru officers?\n&gt;\n&gt; [Non-text portions of this message have been removed]\n&gt;\n&gt; \n\n"
}